github_user_activity_ehdlg/__init__.py
github_user_activity_ehdlg/__main__.py
github_user_activity_ehdlg/utils.py
github_user_activity_ehdlg-1.0.0.dist-info/METADATA
github_user_activity_ehdlg-1.0.0.dist-info/WHEEL
github_user_activity_ehdlg-1.0.0.dist-info/entry_points.txt
github_user_activity_ehdlg-1.0.0.dist-info/top_level.txt
github_user_activity_ehdlg-1.0.0.dist-info/RECORD
