Metadata-Version: 2.1
Name: github-user-activity-ehdlg
Version: 1.0.0
Summary: CLI application that fetches an ddisplays the recent activity of a specified GitHub user
Author: Enrique Hidalgo
Project-URL: Homepage, https://github.com/ehdlg/github-user-activity
Keywords: github,cli
Requires-Python: >=3.9
Requires-Dist: requests
